selenium_2captcha_solver/__init__.py
selenium_2captcha_solver/solver.py
selenium_2captcha_solver-0.1.1.dist-info/LICENSE
selenium_2captcha_solver-0.1.1.dist-info/WHEEL
selenium_2captcha_solver-0.1.1.dist-info/METADATA
selenium_2captcha_solver-0.1.1.dist-info/RECORD
