Metadata-Version: 2.1
Name: selenium-2captcha-solver
Version: 0.1.1
Summary: 
Author: Your Name
Author-email: you@example.com
Requires-Python: >3.8
Classifier: Programming Language :: Python :: 3
Classifier: Programming Language :: Python :: 3.9
Classifier: Programming Language :: Python :: 3.10
Classifier: Programming Language :: Python :: 3.11
Requires-Dist: 2captcha-python (>=1.2.0,<2.0.0)
Requires-Dist: selenium (>=4.10.0,<5.0.0)
